Metadata-Version: 2.1
Name: pagseguroCTS123
Version: 0.0.5
Summary: SDK pagseguro
Home-page: https://pypi.org/project/pagseguro123/
Author: SDK_PS
Author-email: leopoldo.bernardes@monetizze.com.br
License: MIT License
Keywords: pagseguro
Platform: UNKNOWN
License-File: LICENSE
